chris/__init__.py
chris/utils/__init__.py
chris/utils/enum/__init__.py
chris/utils/enum/_enum.py
chris/utils/env/__init__.py
chris/utils/env/_env_setting.py
chris/utils/io/__init__.py
chris/utils/io/_io_utils.py
chris_utils-0.1.1.dist-info/WHEEL
chris_utils-0.1.1.dist-info/METADATA
chris_utils-0.1.1.dist-info/RECORD
